watermarkpy/__init__.py
watermarkpy/watermark.py
watermarkpy_image-0.9.3.dist-info/LICENSE
watermarkpy_image-0.9.3.dist-info/METADATA
watermarkpy_image-0.9.3.dist-info/WHEEL
watermarkpy_image-0.9.3.dist-info/entry_points.txt
watermarkpy_image-0.9.3.dist-info/top_level.txt
watermarkpy_image-0.9.3.dist-info/RECORD
