Metadata-Version: 2.1
Name: watermarkpy-image
Version: 0.9.3
Summary: Add watermark-image in one or multiple images at once.
Home-page: https://github.com/VictorCarlquist/WaterMarkPy
Author: Victor Carlquist
Author-email: victorcarlquist@gmail.com
License: UNKNOWN
Project-URL: Bug Tracker, https://github.com/VictorCarlquist/WaterMarkPy/issues
Platform: UNKNOWN
Classifier: Programming Language :: Python :: 3.7
Classifier: Programming Language :: Python :: 3.8
Classifier: Programming Language :: Python :: 3.9
Classifier: Programming Language :: Python :: 3.10
Classifier: License :: OSI Approved :: MIT License
Classifier: Operating System :: OS Independent
Requires-Python: >=3.7
License-File: LICENSE
